college_board_scraper/__init__.py
college_board_scraper/core.py
college_board_scraper/helpers.py
college_board_scraper-0.3.3.dist-info/METADATA
college_board_scraper-0.3.3.dist-info/WHEEL
college_board_scraper-0.3.3.dist-info/licenses/LICENSE
college_board_scraper-0.3.3.dist-info/RECORD
