Metadata-Version: 2.3
Name: college_board_scraper
Version: 0.3.3
Summary: A package to scrape the CollegeBoard SAT Suite Question Bank webpage.
Project-URL: Homepage, https://github.com/VG-Fish/College-Board/
Author-email: Vishwesswaran Gopal <vishy1290@gmail.com>
License:                     GNU GENERAL PUBLIC LICENSE
License-File: LICENSE
Keywords: collegeboard,scraper
Classifier: Development Status :: 4 - Beta
Classifier: Intended Audience :: Developers
Classifier: License :: OSI Approved :: GNU General Public License (GPL)
Classifier: Natural Language :: English
Classifier: Operating System :: OS Independent
Classifier: Programming Language :: Python :: 3
Classifier: Topic :: Multimedia :: Graphics
Requires-Python: >=3.7
Requires-Dist: selenium
